transject/__init__.py
transject/__version__.py
transject/callbacks.py
transject/config.py
transject/core.py
transject/custom_datasets.py
transject/data_utils.py
transject/layers.py
transject/metrics.py
transject/model_utils.py
transject/models.py
transject/trainer.py
transject/utils.py
transject/__pycache__/__init__.cpython-312.pyc
transject/__pycache__/__version__.cpython-312.pyc
transject/__pycache__/callbacks.cpython-312.pyc
transject/__pycache__/config.cpython-312.pyc
transject/__pycache__/core.cpython-312.pyc
transject/__pycache__/layers.cpython-312.pyc
transject/__pycache__/metrics.cpython-312.pyc
transject/__pycache__/models.cpython-312.pyc
transject/__pycache__/trainer.cpython-312.pyc
transject/__pycache__/utils.cpython-312.pyc
transject-0.1.0.dist-info/licenses/LICENSE
transject-0.1.0.dist-info/METADATA
transject-0.1.0.dist-info/WHEEL
transject-0.1.0.dist-info/top_level.txt
transject-0.1.0.dist-info/RECORD
