Metadata-Version: 2.4
Name: transject
Version: 0.1.0
Summary: Manifold-Preserving Transformer Framework for NLP Tasks
Home-page: https://github.com/parmanu-lcs2/TransJect
Author: Ayan Sengupta, Md. Shad Akhtar, Tanmoy Chakraborty
Author-email: 
License: MIT
Project-URL: Homepage, https://github.com/victor7246/TransJect
Project-URL: Bug Reports, https://github.com/victor7246/TransJect/issues
Project-URL: Source, https://github.com/victor7246/TransJect
Keywords: transformer,manifold-learning,nlp,deep-learning,pytorch,classification,language-modeling
Classifier: Development Status :: 3 - Alpha
Classifier: Intended Audience :: Developers
Classifier: Intended Audience :: Science/Research
Classifier: License :: OSI Approved :: MIT License
Classifier: Programming Language :: Python :: 3
Classifier: Programming Language :: Python :: 3.8
Classifier: Programming Language :: Python :: 3.9
Classifier: Programming Language :: Python :: 3.10
Classifier: Programming Language :: Python :: 3.11
Classifier: Topic :: Scientific/Engineering :: Artificial Intelligence
Requires-Python: >=3.8
License-File: LICENSE
Requires-Dist: torch>=1.12.0
Requires-Dist: transformers>=4.30.0
Requires-Dist: datasets>=2.10.0
Requires-Dist: evaluate>=0.4.0
Requires-Dist: pytorch-lightning>=2.0.0
Requires-Dist: tqdm>=4.65.0
Requires-Dist: numpy>=1.23.0
Requires-Dist: scikit-learn>=1.0.0
Requires-Dist: pandas>=1.3.0
Provides-Extra: dev
Requires-Dist: pytest>=7.0.0; extra == "dev"
Requires-Dist: black>=22.0.0; extra == "dev"
Requires-Dist: flake8>=4.0.0; extra == "dev"
Requires-Dist: jupyter>=1.0.0; extra == "dev"
Provides-Extra: logging
Requires-Dist: wandb>=0.15.0; extra == "logging"
Requires-Dist: tensorboard>=2.11.0; extra == "logging"
Dynamic: home-page
Dynamic: license-file
Dynamic: requires-python
